pyusps-0.0.7-py2.7-nspkg.pth
pyusps-0.0.7.dist-info/METADATA
pyusps-0.0.7.dist-info/namespace_packages.txt
pyusps-0.0.7.dist-info/top_level.txt
pyusps-0.0.7.dist-info/DESCRIPTION.rst
pyusps-0.0.7.dist-info/metadata.json
pyusps-0.0.7.dist-info/WHEEL
pyusps-0.0.7.dist-info/RECORD
pyusps/address_information.py
pyusps/urlutil.py
pyusps/test/util.py
pyusps/test/test_address_information.py
pyusps/test/__init__.py
