Metadata-Version: 2.0
Name: pyusps
Version: 0.0.7
Summary: pyusps -- Python bindings for the USPS Ecommerce APIs
Home-page: https://github.com/thelinuxkid/pyusps
Author: Andres Buritica
Author-email: andres@thelinuxkid.com
License: MIT
Platform: UNKNOWN
Classifier: Development Status :: 4 - Beta
Classifier: Intended Audience :: Developers
Classifier: Natural Language :: English
Classifier: License :: OSI Approved :: MIT License
Classifier: Programming Language :: Python
Classifier: Programming Language :: Python :: 2.7
Classifier: Programming Language :: Python :: 3.5
Requires-Dist: setuptools (>=0.6c11)
Requires-Dist: lxml (>=2.3.3)
Provides-Extra: dev
Requires-Dist: ipython (>=0.12.1); extra == 'dev'
Provides-Extra: test
Requires-Dist: fudge (>=1.0.3); extra == 'test'
Requires-Dist: nose (>=1.1.2); extra == 'test'
